galpos/__init__.py
galpos/orbits.py
galpos/poses.py
galpos/decorate/__init__.py
galpos/decorate/anastristng_decorate.py
galpos/decorate/pynbody_decorate.py
galpos/decorate/util.py
galpos/plot/__init__.py
galpos/plot/pose_trajectory.py
galpos/plot/sfh.py
galpos/plot/sfh_util.py
galpos-1.0.1.dist-info/licenses/LICENSE
galpos-1.0.1.dist-info/METADATA
galpos-1.0.1.dist-info/WHEEL
galpos-1.0.1.dist-info/top_level.txt
galpos-1.0.1.dist-info/RECORD
