Metadata-Version: 2.4
Name: galpos
Version: 1.0.1
Summary: A package for modeling galaxy poses and trajectories.
Author-email: Shuai LU <lushuai@stu.xmu.edu.cn>
License-Expression: MIT
Project-URL: Repository, https://github.com/GalaxySimAnalytics/GalaxyPose
Project-URL: Github, https://github.com/GalaxySimAnalytics/GalaxyPose
Classifier: Programming Language :: Python :: 3
Classifier: Intended Audience :: Science/Research
Classifier: Topic :: Scientific/Engineering :: Astronomy
Classifier: Topic :: Scientific/Engineering :: Physics
Requires-Python: >=3.9
License-File: LICENSE
Requires-Dist: numpy
Requires-Dist: scipy
Provides-Extra: plot
Requires-Dist: matplotlib; extra == "plot"
Provides-Extra: decorate
Requires-Dist: pynbody; extra == "decorate"
Provides-Extra: decorate-tng
Requires-Dist: pynbody; extra == "decorate-tng"
Provides-Extra: tests
Requires-Dist: pytest; extra == "tests"
Requires-Dist: pytest-cov; extra == "tests"
Provides-Extra: dev
Requires-Dist: pre-commit; extra == "dev"
Requires-Dist: mypy>=1.17; extra == "dev"
Requires-Dist: ruff>=0.11; extra == "dev"
Dynamic: license-file
